[
  {
	"id": 1001,
	"name": "瓶盖",
	"grade": 1,
	"star": 0,
	"icon_res": "Icon_Item_1001",
	"price": 1,
	"type": 1,
	"is_in_gacha": false,
	"some_long_value": 38273232,
	"some_double_value": 42.332,
	"some_vec3": {
	  "x": 36.21,
	  "y": 11.2,
	  "z": 10
	}
  },
  {
	"id": 2001,
	"name": "引力发生装置",
	"grade": 1,
	"star": 1,
	"icon_res": "Icon_Item_2002",
	"price": 112.5,
	"type": 2,
	"is_in_gacha": true,
	"some_long_value": 83628263,
	"some_double_value": 12.332,
	"some_vec3": {
	  "x": 12,
	  "y": 36.2,
	  "z": 5.88
	}
  },
  {
	"id": 3001,
	"name": "小黄鸭发射器",
	"grade": 2,
	"star": 1,
	"icon_res": "Icon_Item_3001",
	"price": 50,
	"type": 3,
	"is_in_gacha": true,
	"some_long_value": 43183232,
	"some_double_value": 1238.897543,
	"some_vec3": {
	  "x": 1,
	  "y": 2,
	  "z": 3
	}
  },
  {
	"id": 3003,
	"name": "老式机枪",
	"grade": 1,
	"star": 1,
	"icon_res": "Icon_Item_3003",
	"price": 10,
	"type": 3,
	"is_in_gacha": false,
	"some_long_value": 0,
	"some_double_value": 0,
	"some_vec3": {
	  "x": 0,
	  "y": 0,
	  "z": 0
	}
  }
]
